.gitignore
MANIFEST.in
README.rst
setup.py
collective/.DS_Store
collective/__init__.py
collective/__init__.pyc
collective.ptg.galleriffic.egg-info/PKG-INFO
collective.ptg.galleriffic.egg-info/SOURCES.txt
collective.ptg.galleriffic.egg-info/dependency_links.txt
collective.ptg.galleriffic.egg-info/entry_points.txt
collective.ptg.galleriffic.egg-info/namespace_packages.txt
collective.ptg.galleriffic.egg-info/not-zip-safe
collective.ptg.galleriffic.egg-info/requires.txt
collective.ptg.galleriffic.egg-info/top_level.txt
collective/ptg/.DS_Store
collective/ptg/__init__.py
collective/ptg/__init__.pyc
collective/ptg/galleriffic/.DS_Store
collective/ptg/galleriffic/__init__.py
collective/ptg/galleriffic/__init__.pyc
collective/ptg/galleriffic/configure.zcml
collective/ptg/galleriffic/galleriffic.pt
collective/ptg/galleriffic/i18n.sh
collective/ptg/galleriffic/locales/.DS_Store
collective/ptg/galleriffic/locales/collective.ptg.galleriffic.pot
collective/ptg/galleriffic/locales/manual.pot
collective/ptg/galleriffic/locales/de/LC_MESSAGES/collective.ptg.galleriffic.mo
collective/ptg/galleriffic/locales/de/LC_MESSAGES/collective.ptg.galleriffic.po
collective/ptg/galleriffic/locales/es/LC_MESSAGES/collective.ptg.galleriffic.mo
collective/ptg/galleriffic/locales/es/LC_MESSAGES/collective.ptg.galleriffic.po
collective/ptg/galleriffic/locales/eu/LC_MESSAGES/collective.ptg.galleriffic.mo
collective/ptg/galleriffic/locales/eu/LC_MESSAGES/collective.ptg.galleriffic.po
collective/ptg/galleriffic/locales/fi/LC_MESSAGES/collective.ptg.galleriffic.mo
collective/ptg/galleriffic/locales/fi/LC_MESSAGES/collective.ptg.galleriffic.po
collective/ptg/galleriffic/locales/fr/LC_MESSAGES/collective.ptg.galleriffic.mo
collective/ptg/galleriffic/locales/fr/LC_MESSAGES/collective.ptg.galleriffic.po
collective/ptg/galleriffic/locales/it/LC_MESSAGES/collective.ptg.galleriffic.mo
collective/ptg/galleriffic/locales/it/LC_MESSAGES/collective.ptg.galleriffic.po
collective/ptg/galleriffic/locales/nl/LC_MESSAGES/collective.ptg.galleriffic.mo
collective/ptg/galleriffic/locales/nl/LC_MESSAGES/collective.ptg.galleriffic.po
collective/ptg/galleriffic/locales/no/LC_MESSAGES/collective.ptg.galleriffic.mo
collective/ptg/galleriffic/locales/no/LC_MESSAGES/collective.ptg.galleriffic.po
collective/ptg/galleriffic/locales/pt_BR/LC_MESSAGES/collective.ptg.galleriffic.mo
