Metadata-Version: 1.0
Name: collective.ptg.galleriffic
Version: 1.1.2
Summary: UNKNOWN
Home-page: https://github.com/collective/collective.ptg.galleriffic
Author: Nathan Van Gheem
Author-email: vangheem@gmail.com
License: GPL
Keywords: plone plonetruegallery gallery addon
Platform: UNKNOWN
Classifier: Framework :: Plone
Classifier: Programming Language :: Python
